CloudshellController/__init__.py
CloudshellController-0.12.data/data/my_data/data_file
CloudshellController-0.12.dist-info/DESCRIPTION.rst
CloudshellController-0.12.dist-info/METADATA
CloudshellController-0.12.dist-info/RECORD
CloudshellController-0.12.dist-info/WHEEL
CloudshellController-0.12.dist-info/metadata.json
CloudshellController-0.12.dist-info/top_level.txt
