Metadata-Version: 2.0
Name: CloudshellController
Version: 0.12
Summary: Quali API Wrapper
Home-page: https://github.com/Madslick/CloudshellController
Author: Joe Auby
Author-email: joeyauby@gmail.com
License: MIT
Keywords: cloudshell,Quali,pypi,package
Platform: UNKNOWN
Classifier: Development Status :: 3 - Alpha
Classifier: Intended Audience :: Developers
Classifier: License :: OSI Approved :: MIT License
Classifier: Operating System :: OS Independent
Classifier: Programming Language :: Python
Classifier: Programming Language :: Python :: 2
Classifier: Programming Language :: Python :: 2.7
Requires-Dist: cloudshell-automation-api
